nyxus/__init__.py
nyxus/_version.py
nyxus/backend.cpython-311-x86_64-linux-gnu.so
nyxus/functions.py
nyxus/nyxus.py
nyxus_cuda11x.libs/libarrow-f0a61fc3.so.2000.0.0
nyxus_cuda11x.libs/libblosc-4f8b1663.so.1.21.6
nyxus_cuda11x.libs/libcmr-c6dada90.so.19.3.6.9
nyxus_cuda11x.libs/libdcmdata-bedfb7af.so.19.3.6.9
nyxus_cuda11x.libs/libdcmdsig-057ba9f4.so.19.3.6.9
nyxus_cuda11x.libs/libdcmect-4795bad4.so.19.3.6.9
nyxus_cuda11x.libs/libdcmfg-cc676540.so.19.3.6.9
nyxus_cuda11x.libs/libdcmimage-c447868d.so.19.3.6.9
nyxus_cuda11x.libs/libdcmimgle-9fe04da9.so.19.3.6.9
nyxus_cuda11x.libs/libdcmiod-7296521a.so.19.3.6.9
nyxus_cuda11x.libs/libdcmjpeg-eaa27a2f.so.19.3.6.9
nyxus_cuda11x.libs/libdcmjpls-ff499621.so.19.3.6.9
nyxus_cuda11x.libs/libdcmnet-d5919c8c.so.19.3.6.9
nyxus_cuda11x.libs/libdcmpmap-97445b02.so.19.3.6.9
nyxus_cuda11x.libs/libdcmpstat-ff5d2060.so.19.3.6.9
nyxus_cuda11x.libs/libdcmqrdb-bccb3180.so.19.3.6.9
nyxus_cuda11x.libs/libdcmrt-6e6def03.so.19.3.6.9
nyxus_cuda11x.libs/libdcmseg-abae7c8e.so.19.3.6.9
nyxus_cuda11x.libs/libdcmsr-ce68d802.so.19.3.6.9
nyxus_cuda11x.libs/libdcmtkcharls-fc1b1798.so.19.3.6.9
nyxus_cuda11x.libs/libdcmtls-6ba66307.so.19.3.6.9
nyxus_cuda11x.libs/libdcmtract-c432fd29.so.19.3.6.9
nyxus_cuda11x.libs/libdcmwlm-eb91646a.so.19.3.6.9
nyxus_cuda11x.libs/libdcmxml-897c6471.so.19.3.6.9
nyxus_cuda11x.libs/libdeflate-a598a175.so.0
nyxus_cuda11x.libs/libfmjpeg2k-918f6f5e.so.1.0.3
nyxus_cuda11x.libs/libi2d-cde7b296.so.19.3.6.9
nyxus_cuda11x.libs/libijg12-624fe9bc.so.19.3.6.9
nyxus_cuda11x.libs/libijg16-859c617f.so.19.3.6.9
nyxus_cuda11x.libs/libijg8-c2883798.so.19.3.6.9
nyxus_cuda11x.libs/libjpeg-6534214e.so.62.4.0
nyxus_cuda11x.libs/liboficonv-2c5bfa4e.so.19.3.6.9
nyxus_cuda11x.libs/liboflog-1180842e.so.19.3.6.9
nyxus_cuda11x.libs/libofstd-20f6afd4.so.19.3.6.9
nyxus_cuda11x.libs/libopenjp2-7d041df5.so.2.5.0
nyxus_cuda11x.libs/libparquet-4fdfb002.so.2000.0.0
nyxus_cuda11x.libs/libpng16-3afffc43.so.16.53.0
nyxus_cuda11x-0.10.0.dist-info/METADATA
nyxus_cuda11x-0.10.0.dist-info/WHEEL
nyxus_cuda11x-0.10.0.dist-info/top_level.txt
nyxus_cuda11x-0.10.0.dist-info/RECORD
nyxus_cuda11x-0.10.0.dist-info/licenses/LICENSE
